Vibrationology_Interactive_GUI_demo/__init__.py
Vibrationology_Interactive_GUI_demo/maindemo.py
Vibrationology_Interactive_GUI_demo/page0.py
Vibrationology_Interactive_GUI_demo/page1.py
Vibrationology_Interactive_GUI_demo/page1_n.py
Vibrationology_Interactive_GUI_demo/page2.py
Vibrationology_Interactive_GUI_demo/page2_n.py
Vibrationology_Interactive_GUI_demo/page3.py
Vibrationology_Interactive_GUI_demo/page3_n.py
Vibrationology_Interactive_GUI_demo/page4.py
Vibrationology_Interactive_GUI_demo/page4_n.py
Vibrationology_Interactive_GUI_demo/page_0.py
Vibrationology_Interactive_GUI_demo/page_1.py
Vibrationology_Interactive_GUI_demo/page_2.py
Vibrationology_Interactive_GUI_demo/page_3.py
Vibrationology_Interactive_GUI_demo/page_4.py
Vibrationology_Interactive_GUI-1.0.1.dist-info/METADATA
Vibrationology_Interactive_GUI-1.0.1.dist-info/WHEEL
Vibrationology_Interactive_GUI-1.0.1.dist-info/entry_points.txt
Vibrationology_Interactive_GUI-1.0.1.dist-info/top_level.txt
Vibrationology_Interactive_GUI-1.0.1.dist-info/RECORD
