Metadata-Version: 2.1
Name: Vibrationology_Interactive_GUI
Version: 1.0.1
Summary: Description of my project
Author: LI XIANG XIAN FENG
Author-email: 346585407@qq.com
Requires-Dist: matplotlib
Requires-Dist: numpy
Requires-Dist: scipy
Requires-Dist: vpython
